README.md
setup.cfg
setup.py
captcha22/__init__.py
captcha22/__main__.py
captcha22.egg-info/PKG-INFO
captcha22.egg-info/SOURCES.txt
captcha22.egg-info/dependency_links.txt
captcha22.egg-info/entry_points.txt
captcha22.egg-info/requires.txt
captcha22.egg-info/top_level.txt
captcha22/lib/__init__.py
captcha22/lib/api/__init__.py
captcha22/lib/api/captcha_solve.py
captcha22/lib/api/client.py
captcha22/lib/api/server.py
captcha22/lib/api/ui.py
captcha22/lib/core/__init__.py
captcha22/lib/core/client.py
captcha22/lib/core/server.py
captcha22/lib/crackers/__init__.py
captcha22/lib/crackers/captcha.py
captcha22/lib/crackers/pyppeteer.py
captcha22/lib/labels/__init__.py
captcha22/lib/labels/generator.py
captcha22/lib/labels/labeller.py
captcha22/lib/labels/labeller_legacy.py
captcha22/lib/server/__init__.py
captcha22/lib/server/captcha22.py