Metadata-Version: 1.1
Name: captcha22
Version: 1.0.5
Summary: CAPTCHA Cracking Server and Client based on Tensorflow, attention-ocr and Flask. 
Home-page: https://github.com/FSecureLABS/captcha22/
Author: Tinus Green
Author-email: work@tinusgreen.co.za
License: MIT
Download-URL: https://github.com/FSecureLABS/captcha22/archive/v1.0.5.tar.gz
Platform: UNKNOWN
